schemactl/__init__.py
schemactl/adapters/alembic.py
schemactl/adapters/database.py
schemactl/cli.py
schemactl/config.py
schemactl/services/__init__.py
schemactl/services/migration.py
schemactl/services/model_loader.py
schemactl-0.2.1.dist-info/METADATA
schemactl-0.2.1.dist-info/WHEEL
schemactl-0.2.1.dist-info/entry_points.txt
schemactl-0.2.1.dist-info/RECORD
