Metadata-Version: 2.4
Name: schemactl
Version: 0.2.1
Summary: next‑generation database migration tool
License: MIT
Author: Teams
Author-email: teams@dotlabs.dev
Requires-Python: >=3.12,<4.0
Classifier: License :: OSI Approved :: MIT License
Classifier: Programming Language :: Python :: 3
Classifier: Programming Language :: Python :: 3.12
Classifier: Programming Language :: Python :: 3.13
Classifier: Programming Language :: Python :: 3.14
Requires-Dist: alembic (>=1.17.2,<2.0.0)
Requires-Dist: asyncpg (>=0.31.0,<0.32.0)
Requires-Dist: click (>=8.3.1,<9.0.0)
Requires-Dist: greenlet (>=3.3.0,<4.0.0)
Requires-Dist: python-dotenv (>=1.2.1,<2.0.0)
Requires-Dist: rich (>=14.2.0,<15.0.0)
Requires-Dist: sqlalchemy (>=2.0.45,<3.0.0)
